tfmx/__init__.py
tfmx/config_qwen3_embedding_06b.json
tfmx/config_sentence_transformers.json
tfmx/embed_client.py
tfmx/embed_server.py
tfmx/gpu_ctl.py
tfmx/gpu_fan.py
tfmx/gpu_mon.py
tfmx/gpu_pow.py
tfmx/llm.py
tfmx/lsh.py
tfmx/perf_tracker.py
tfmx/tei_benchmark.py
tfmx/tei_benchtext.py
tfmx/tei_client.py
tfmx/tei_clients.py
tfmx/tei_clients_cli.py
tfmx/tei_clients_core.py
tfmx/tei_clients_stats.py
tfmx/tei_compose.py
tfmx/tei_machine.py
tfmx/tei_performance.py
tfmx/tei_scheduler.py
tfmx/test_gpu_lsh.py
tfmx/vector_utils.py
tfmx-0.8.dist-info/licenses/LICENSE
tfmx-0.8.dist-info/METADATA
tfmx-0.8.dist-info/WHEEL
tfmx-0.8.dist-info/entry_points.txt
tfmx-0.8.dist-info/top_level.txt
tfmx-0.8.dist-info/RECORD
