Metadata-Version: 2.4
Name: tfmx
Version: 0.8
Summary: Serve Transformers and Manage GPUs
Author: Hansimov
License-Expression: MIT
Project-URL: Homepage, https://github.com/Hansimov/tfmx
Project-URL: Issues, https://github.com/Hansimov/tfmx/issues
Classifier: Programming Language :: Python :: 3
Classifier: Operating System :: OS Independent
Requires-Python: >=3.6
License-File: LICENSE
Requires-Dist: tclogger
Requires-Dist: numpy
Requires-Dist: requests
Requires-Dist: fastapi
Requires-Dist: uvicorn
Requires-Dist: httpx
Requires-Dist: webu
Requires-Dist: orjson
Dynamic: license-file
